[
  {
    "symbol": "ETH",
    "signal": "WEAK_BUY",
    "score": 8.0,
    "price": 1964.07,
    "change_24h": -3.81359,
    "reasons": [
      "趋势：趋势加速",
      "动量：低位运行",
      "情绪：bullish (score=1, articles=10)",
      "成交量：高换手率 | 高流动性"
    ],
    "warnings": [],
    "timestamp": "2026-03-04T05:36:11.525162",
    "suggested_position": 0.032,
    "suggested_amount_usd": 9.51571947548331,
    "stop_loss": 1865.8664999999999,
    "take_profit": 2356.884,
    "risk_reward_ratio": 4.0
  },
  {
    "symbol": "BNB",
    "signal": "WEAK_BUY",
    "score": 5.0,
    "price": 629.31,
    "change_24h": -0.90945,
    "reasons": [
      "趋势：趋势加速",
      "动量：低位运行",
      "情绪：bullish (score=1, articles=10)",
      "成交量： | 高流动性"
    ],
    "warnings": [],
    "timestamp": "2026-03-04T05:36:11.525172",
    "suggested_position": 0.032,
    "suggested_amount_usd": 9.51571947548331,
    "stop_loss": 597.8444999999999,
    "take_profit": 755.1719999999999,
    "risk_reward_ratio": 4.0
  },
  {
    "symbol": "BTC",
    "signal": "HOLD",
    "score": 4.0,
    "price": 67946,
    "change_24h": -2.11976,
    "reasons": [
      "趋势：趋势加速",
      "动量：中性",
      "情绪：neutral (score=0, articles=10)",
      "成交量： | 高流动性"
    ],
    "warnings": [],
    "timestamp": "2026-03-04T05:36:11.525114",
    "suggested_position": 0,
    "suggested_amount_usd": 0.0,
    "stop_loss": 64548.7,
    "take_profit": 81535.2,
    "risk_reward_ratio": 4.0
  },
  {
    "symbol": "SOL",
    "signal": "HOLD",
    "score": 2.0,
    "price": 84.45,
    "change_24h": -3.52877,
    "reasons": [
      "趋势：趋势加速",
      "动量：低位运行",
      "情绪：bearish (score=-1, articles=10)",
      "成交量：高换手率 | 高流动性"
    ],
    "warnings": [],
    "timestamp": "2026-03-04T05:36:11.525191",
    "suggested_position": 0,
    "suggested_amount_usd": 0.0,
    "stop_loss": 80.22749999999999,
    "take_profit": 101.34,
    "risk_reward_ratio": 4.0
  },
  {
    "symbol": "XRP",
    "signal": "HOLD",
    "score": 0.0,
    "price": 1.35,
    "change_24h": -3.08976,
    "reasons": [
      "趋势：趋势加速",
      "动量：接近 24h 低点",
      "情绪：neutral (score=0, articles=10)",
      "成交量： | 高流动性"
    ],
    "warnings": [],
    "timestamp": "2026-03-04T05:36:11.525183",
    "suggested_position": 0,
    "suggested_amount_usd": 0.0,
    "stop_loss": 1.2825,
    "take_profit": 1.62,
    "risk_reward_ratio": 4.0
  },
  {
    "symbol": "DOGE",
    "signal": "WEAK_SELL",
    "score": -8.5,
    "price": 0.088773,
    "change_24h": -5.8479,
    "reasons": [
      "趋势：下跌趋势 (-5.8%), 趋势减速",
      "动量：接近 24h 低点",
      "情绪：neutral (score=0, articles=10)",
      "成交量：正常换手 | 高流动性"
    ],
    "warnings": [],
    "timestamp": "2026-03-04T05:36:11.525207",
    "suggested_position": 0.032,
    "suggested_amount_usd": 9.51571947548331,
    "stop_loss": 0.08433435,
    "take_profit": 0.1065276,
    "risk_reward_ratio": 4.0
  },
  {
    "symbol": "ADA",
    "signal": "WEAK_SELL",
    "score": -11.5,
    "price": 0.261102,
    "change_24h": -6.4419,
    "reasons": [
      "趋势：下跌趋势 (-6.4%), 趋势减速",
      "动量：接近 24h 低点",
      "情绪：bearish (score=-1, articles=10)",
      "成交量：正常换手 | 高流动性"
    ],
    "warnings": [],
    "timestamp": "2026-03-04T05:36:11.525217",
    "suggested_position": 0.032,
    "suggested_amount_usd": 9.51571947548331,
    "stop_loss": 0.2480469,
    "take_profit": 0.3133224,
    "risk_reward_ratio": 4.0
  }
]