{
  "deployment_date": "2026-03-02",
  "projects": {
    "project_1": {
      "name": "x402 API",
      "status": "运行中",
      "url": "http://localhost:5001",
      "mode": "模拟模式",
      "files": [
        "app_demo.py - 模拟模式服务器",
        "app_full.py - 完整版（需有效 API Key）",
        ".env - 配置文件"
      ],
      "endpoints": [
        "GET /health - 健康检查",
        "GET /api/v1/stats - 统计信息",
        "POST /api/v1/architect - 架构设计 ($0.10)",
        "POST /api/v1/code-gen - 代码生成 ($0.08)",
        "POST /api/v1/code-audit - 代码审计 ($0.05)",
        "POST /api/v1/logic - 逻辑推理 ($0.06)",
        "POST /api/v1/translate - 翻译 ($0.02)",
        "POST /api/v1/long-text - 长文解析 ($0.03)",
        "POST /api/v1/crawl - 网络爬虫 ($0.04)",
        "POST /api/v1/vision - 视觉解析 ($0.15)"
      ],
      "note": "API Key 无效，当前运行在模拟模式。需要有效的阿里百炼 API Key 才能调用真实 AI 模型。"
    },
    "project_2": {
      "name": "x402 Python SDK",
      "status": "完成",
      "location": "/home/admin/Ziwei/projects/x402-python-sdk/",
      "files": [
        "x402/__init__.py - SDK 入口",
        "x402/client.py - 客户端",
        "x402/payment.py - 支付处理",
        "x402/exceptions.py - 异常定义",
        "examples/basic_usage.py - 使用示例",
        "test_sdk.py - 测试脚本",
        "README.md - 文档"
      ],
      "features": [
        "自动处理 HTTP 402 支付",
        "支付证明生成和验证",
        "简化的 API 调用",
        "错误处理"
      ]
    },
    "project_3": {
      "name": "x402 交易机器人",
      "status": "完成（模拟）",
      "location": "/home/admin/Ziwei/projects/x402-trading-bot/",
      "files": [
        "bot_simple.py - 简化版交易机器人"
      ],
      "tokens": [
        "VIRTUAL - $1.40",
        "PAYAI - $0.05",
        "PING - $0.03",
        "HEU - $0.04"
      ],
      "warning": "⚠️ 仅用于学习，不要使用真实资金！"
    }
  },
  "expected_revenue": {
    "monthly": 2800,
    "yearly": 33600,
    "breakdown": {
      "api": 1500,
      "sdk": 1300
    }
  },
  "next_steps": [
    "1. 获取有效的阿里百炼 API Key",
    "2. 更新 .env 文件中的 DASHSCOPE_API_KEY",
    "3. 重启服务使用真实 AI 模型",
    "4. 部署到公网服务器",
    "5. 准备 CodeCanyon 上架材料（项目 2）"
  ],
  "api_key_issue": "提供的 API Key 无效，需要重新获取有效的阿里百炼 API Key"
}